[{"original_request_url": "https://m.facebook.com/5835075533277831", "post_url": "https://m.facebook.com/5835075533277831"},
{"original_request_url": "https://m.facebook.com/5833844366734281", "post_url": "https://m.facebook.com/5833844366734281"},
{"original_request_url": "https://m.facebook.com/5824889147629803", "post_url": "https://m.facebook.com/5824889147629803"},
{"original_request_url": "https://m.facebook.com/5528618587256862", "post_url": "https://m.facebook.com/5528618587256862"},
{"original_request_url": "https://m.facebook.com/5833221840129867", "post_url": "https://m.facebook.com/5833221840129867"},
{"original_request_url": "https://m.facebook.com/5432875503497838", "post_url": "https://m.facebook.com/5432875503497838"},
{"original_request_url": "https://m.facebook.com/5831809423604442", "post_url": "https://m.facebook.com/5831809423604442"},
{"original_request_url": "https://m.facebook.com/5877445765707474", "post_url": "https://m.facebook.com/5877445765707474"},
{"original_request_url": "https://m.facebook.com/5507904542661600", "post_url": "https://m.facebook.com/5507904542661600"},
{"original_request_url": "https://m.facebook.com/5556848024433918", "post_url": "https://m.facebook.com/5556848024433918"},
{"original_request_url": "https://m.facebook.com/5310771419041581", "post_url": "https://m.facebook.com/5310771419041581"},
{"original_request_url": "https://m.facebook.com/5831310666987651", "post_url": "https://m.facebook.com/5831310666987651"},
{"original_request_url": "https://m.facebook.com/5779399725512079", "post_url": "https://m.facebook.com/5779399725512079"},
{"original_request_url": "https://m.facebook.com/5749261791859206", "post_url": "https://m.facebook.com/5749261791859206"},
{"original_request_url": "https://m.facebook.com/5795071787278206", "post_url": "https://m.facebook.com/5795071787278206"},
{"original_request_url": "https://m.facebook.com/5753768361408549", "post_url": "https://m.facebook.com/5753768361408549"},
{"original_request_url": "https://m.facebook.com/5726386194146766", "post_url": "https://m.facebook.com/5726386194146766"},
{"original_request_url": "https://m.facebook.com/5759268060858579", "post_url": "https://m.facebook.com/5759268060858579"},
{"original_request_url": "https://m.facebook.com/5523236187795102", "post_url": "https://m.facebook.com/5523236187795102"},
{"original_request_url": "https://m.facebook.com/5543896132395774", "post_url": "https://m.facebook.com/5543896132395774"}]